Metadata-Version: 2.1
Name: selfbotUtils
Version: 0.0.3
Summary: A python module that makes selfbot creation extremely easy, without risking your account being phonebanned!
Home-page: https://github.com/adam757521/selfbotUtils
Author: adam7100
License: MIT
Download-URL: https://github.com/adam757521/selfbotUtils/archive/refs/tags/v0.0.3.tar.gz
Keywords: python,sniper,discord,selfbot,discord-py,invite,user-friendly,friendly,discordbots
Platform: UNKNOWN
Classifier: Development Status :: 3 - Alpha
Classifier: Intended Audience :: Developers
Classifier: Topic :: Software Development :: Build Tools
Classifier: License :: OSI Approved :: MIT License
Classifier: Programming Language :: Python :: 3
Classifier: Programming Language :: Python :: 3.4
Classifier: Programming Language :: Python :: 3.5
Classifier: Programming Language :: Python :: 3.6
